refreshrate/__init__.py
refreshrate-0.4.dist-info/LICENSE
refreshrate-0.4.dist-info/METADATA
refreshrate-0.4.dist-info/WHEEL
refreshrate-0.4.dist-info/top_level.txt
refreshrate-0.4.dist-info/RECORD
