Metadata-Version: 2.1
Name: refreshrate
Version: 0.4
Summary: A python package that fetchs your monitor refresh rate.
Home-page: https://github.com/ruskydev/refreshrate
Author: Ayaan
Author-email: iamayaanalee@gmail.com
Classifier: Programming Language :: Python :: 3
Classifier: License :: OSI Approved :: MIT License
Classifier: Operating System :: OS Independent
Requires-Python: >=3.6
License-File: LICENSE
Requires-Dist: wmi
